{
  "3": "……真厉害呢，Miku",
  "4": "感谢你的聆听，Miku",
  "7": "我真的非常想去试试！",
  "11": "我觉得很尴尬，所以不要告诉其他人，好吗？ ",
  "15": "真的演奏得七零八落呢。但是…… ",
  "19": "明天要加油呢，Miku！ ",
  "23": "我，已经不是偶像了",
  "27": "实乃里！掉拍了喔！ ",
  "31": "做这份工作很开心喔。但是……",
  "35": "我，有稍微改变一点了吗",
  "39": "欢迎光临！这里有位置喔！",
  "43": "就用我们的歌击溃掉那群家伙",
  "47": "我早就，应该要这样做了",
  "51": "……啥？初、初音、未来……？",
  "55": "要怎么欢迎呢～☆",
  "59": "用机器人演戏什么的，也太蠢了吧",
  "63": "下次有机会再继续演这出戏！",
  "67": "得快点作曲才行。 ……咦？",
  "71": "我啊，才不是什么「好孩子」喔",
  "75": "……啊～啊。我到底，在做什么啊",
  "79": "我今天也很可爱呢～♪",
  "87": "快点，找到吧……",
  "88": "今天一起上台吧！",
  "91": "想要带给大～家活力喔！",
  "92": "真是的，我不管连了啦！",
  "95": "我……要去铃那里",
  "96": "这个sekai，真的很有趣呢！",
  "99": "好了，你也一起",
  "103": "只喝1杯就好如何呢？",
  "107": "大、大家，要去哪里啊？",
  "109": "想要去……见大家呢",
  "110": "只要慢慢来的话，就没问题了喔",
  "111": "就是因为都不把重要的事情说出来",
  "114": "……感觉好不舒服……",
  "115": "一定会——拯救的喔",
  "116": "又被奏他们找到了呢",
  "119": "不像是平常的我……？",
  "120": "为什么我会遇到这种事情—！",
  "121": "我觉得一起跨越就好了喔",
  "124": "那么要赢喔！ ！",
  "125": "回来学校真是太好了",
  "126": "呀呵～！我来加油了喔～！",
  "129": "多亏你让我想起重要的事情了",
  "130": "啊哇哇哇，小雫等等～！",
  "131": "要唱我珍藏的歌曲喔！",
  "134": "我，最差劲了……！",
  "135": "因为我接下来也会继续加油的！",
  "136": "别开玩笑了。守护是怎样啊",
  "137": "或许我也很享受呢",
  "139": "跟大家一起吵吵闹闹也不错呢",
  "140": "这样的话正式上场也会很完美了呢！",
  "141": "要演出神高史上最棒的戏喔！",
  "144": "感觉就像是从天空降下了礼物",
  "145": "要演出闪闪发光的秀喔～☆",
  "146": "我想到好主意了！",
  "149": "不觉得赶快投降比较好吗？",
  "150": "铃果然是最棒的搭档了！",
  "151": "不用在意喔穗波。对吧？",
  "152": "意外的，这1年下来或许还不错呢",
  "155": "请让我表达一下意见",
  "156": "这也算是某种缘分吧。请多指教喔",
  "157": "太好了呢，穗波",
  "160": "那个啊，大家……希望可以听我说一下",
  "161": "我是新成员，巡音流歌喔",
  "162": "真是的，这占卜是怎样啊",
  "165": "请听一下现在的我的觉悟",
  "166": "很努力了呢，冬弥",
  "167": "好了，喝下这个打起精神来！",
  "170": "……没事，没什么啦所以",
  "171": "温暖的笑容会闪闪发光喔☆",
  "172": "不、不要过来这里～！",
  "175": "我也，还不想要放弃！",
  "176": "画到被认可为止不就好了",
  "177": "我现在能做到的事是……",
  "180": "胸口暖和和的～！",
  "181": "如果变得想说的话要说出来喔……",
  "182": "希望你能不要再继续侮辱我的同伴了",
  "185": "是我很宝贵的雏人偶喔！",
  "186": "唉……为什么会发生这种事情……",
  "187": "如果能感到高兴就好了呢",
  "190": "传达给，那孩子吧——！",
  "191": "实乃里，一直都是个偶像喔",
  "192": "喵～？",
  "195": "总有一天，要作出能传达到那片天空的曲子——",
  "196": "我……想要知道我自己的事情",
  "197": "好厉害。竟然能像那样威风凛凛的……",
  "198": "让我听听看吧。现在的一歌的歌曲",
  "199": "要能够赶快跟上大家的脚步！",
  "202": "这还是第一次，想着明年也一起之类的呢",
  "203": "把我当作不存在吧",
  "204": "在、在那里的……是谁……？",
  "207": "就算以后会感到后悔，我也不在乎了",
  "208": "成为专家，到底是什么感觉呢",
  "209": "真想要赶快举办Live试试看呢♪",
  "212": "可不能在这里落败啊",
  "213": "就听那家伙的话一次吧！",
  "214": "我很抱歉！正如你所见！",
  "217": "帮大忙了⋯⋯",
  "218": "这个时候，就用上从综艺节目中锻炼出来的脚力！",
  "219": "希望，吗。维持这种情况，就好了⋯⋯",
  "222": "真、真可爱……！",
  "223": "一起来做小遥想做的事吧",
  "224": "安可！ 安可！",
  "227": "请你——就这样握住我的手",
  "228": "我打算从这里改变一下计划！",
  "229": "所以这将是类的舞台布景！",
  "232": "真是美妙绝伦的景色呢——",
  "233": "一起来创造很——多笑容吧！",
  "234": "能…能够做到的，全部都要尽力而为！",
  "237": "那个花坛，该不会是——",
  "238": "请拯救那个孩子吧",
  "239": "我觉得，真是太好了",
  "240": "目标是咖啡厅，Let's goー！",
  "242": "我有个，无论如何都想传达的事情",
  "243": "那个梦想，绝对不可以放弃喔！",
  "244": "Rin酱，我知道了！",
  "245": "真希望咲希能露出笑容啊",
  "246": "一定有什么是因为是我们才可以传达到的",
  "247": "所以现在就相信着，守护着好吗？",
  "249": "我可以————唱得出来！",
  "250": "终于肯笑了",
  "251": "尝试着更仔细地看看自己，如何？",
  "252": "我觉得这就是我们的风格",
  "254": "是是是，我有好好记得啦",
  "255": "彰人，要不要试试那种？",
  "256": "这鞋子超帅的吧！",
  "257": "啊哈哈！雫真是的！"
}